{
  "word": "addition",
  "ipa": "/ʌdɪʃʌn/",
  "wiktionary_senses": [
    {
      "pos": "noun",
      "definition": "The act of adding anything.",
      "translations_ru": [
        "сложе́ние",
        "прибавле́ние"
      ]
    },
    {
      "pos": "noun",
      "definition": "Anything that is added."
    },
    {
      "pos": "noun",
      "definition": "The arithmetic operation of adding.",
      "translations_ru": [
        "сложе́ние"
      ]
    },
    {
      "pos": "noun",
      "definition": "A dot at the right side of a note as an indication that its sound is to be lengthened one half."
    },
    {
      "pos": "noun",
      "definition": "A title annexed to a person's name to identify him or her more precisely."
    },
    {
      "pos": "noun",
      "definition": "Something added to a coat of arms, as a mark of honour."
    },
    {
      "pos": "noun",
      "definition": "an organic reaction where two or more molecules combine to form a larger one (the adduct)."
    }
  ],
  "relations": {
    "synonyms": [
      "increase",
      "gain"
    ],
    "hypernyms": [
      "increase"
    ]
  }
}