{
  "word": "bend",
  "ipa": "/bɛnd/",
  "wiktionary_senses": [
    {
      "pos": "verb",
      "definition": "To cause (something) to change its shape into a curve, by physical force, chemical action, or any other means."
    },
    {
      "pos": "verb",
      "definition": "To become curved.",
      "translations_ru": [
        "гну́ться",
        "изгиба́ться"
      ]
    },
    {
      "pos": "verb",
      "definition": "To cause to change direction."
    },
    {
      "pos": "verb",
      "definition": "To change direction."
    },
    {
      "pos": "verb",
      "definition": "To be inclined; to direct itself."
    },
    {
      "pos": "verb",
      "definition": "To stoop."
    },
    {
      "pos": "verb",
      "definition": "To bow in prayer, or in token of submission."
    },
    {
      "pos": "verb",
      "definition": "To force to submit."
    },
    {
      "pos": "verb",
      "definition": "To submit."
    },
    {
      "pos": "verb",
      "definition": "To apply to a task or purpose."
    },
    {
      "pos": "verb",
      "definition": "To apply oneself to a task or purpose."
    },
    {
      "pos": "verb",
      "definition": "To adapt or interpret to for a purpose or beneficiary."
    },
    {
      "pos": "verb",
      "definition": "To tie, as in securing a line to a cleat; to shackle a chain to an anchor; make fast."
    },
    {
      "pos": "verb",
      "definition": "To smoothly change the pitch of a note."
    },
    {
      "pos": "verb",
      "definition": "To swing the body when rowing."
    },
    {
      "pos": "noun",
      "definition": "A curve."
    },
    {
      "pos": "noun",
      "definition": "Any of the various knots which join the ends of two lines."
    },
    {
      "pos": "noun",
      "definition": "A severe condition caused by excessively quick decompression, causing bubbles of nitrogen to form in the blood; decompression sickness."
    },
    {
      "pos": "noun",
      "definition": "One of the honourable ordinaries formed by two diagonal lines drawn from the dexter chief to the sinister base; it generally occupies a fifth part of the shield if uncharged, but if charged one third."
    },
    {
      "pos": "noun",
      "definition": "Turn; purpose; inclination; ends."
    },
    {
      "pos": "noun",
      "definition": "In the leather trade, the best quality of sole leather; a butt; sometimes, half a butt cut lengthwise."
    },
    {
      "pos": "noun",
      "definition": "Hard, indurated clay; bind."
    },
    {
      "pos": "noun",
      "definition": "The thickest and strongest planks in a ship's sides, more generally called wales, which have the beams, knees, and futtocks bolted to them."
    },
    {
      "pos": "noun",
      "definition": "The frames or ribs that form the ship's body from the keel to the top of the sides."
    },
    {
      "pos": "noun",
      "definition": "A glissando, or glide between one pitch and another, especially one accomplished by bending a string (such as on guitar)."
    },
    {
      "pos": "name",
      "definition": "A ghost town and former railway community in central British Columbia, Canada. Named after a 90-degree curve in the railway line."
    },
    {
      "pos": "name",
      "definition": "A census-designated place in Tehama County, California, United States."
    },
    {
      "pos": "name",
      "definition": "An unincorporated community in Maries County, Missouri, United States."
    },
    {
      "pos": "name",
      "definition": "A city, the county seat of Deschutes County, Oregon, United States."
    },
    {
      "pos": "name",
      "definition": "An unincorporated community in Meade County, South Dakota, United States."
    },
    {
      "pos": "name",
      "definition": "An unincorporated community in Lampasas County and San Saba County, Texas, United States."
    },
    {
      "pos": "name",
      "definition": "A surname."
    }
  ],
  "relations": {
    "synonyms": [
      "turn",
      "fold"
    ],
    "hypernyms": [
      "turn",
      "movement",
      "move",
      "ordinary"
    ]
  }
}