{
  "word": "curious",
  "ipa": "/kjʊɹiʌs/",
  "wiktionary_senses": [
    {
      "pos": "adj",
      "definition": "Tending to ask questions, or to want to explore or investigate; inquisitive; (with a negative connotation) nosy, prying.",
      "translations_ru": [
        "любопы́тный",
        "любозна́тельный",
        "проявля́ющий интере́с",
        "пытли́вый"
      ]
    },
    {
      "pos": "adj",
      "definition": "Caused by curiosity."
    },
    {
      "pos": "adj",
      "definition": "Leading one to ask questions about; somewhat odd, out of the ordinary, or unusual.",
      "translations_ru": [
        "курьёзный",
        "любопы́тный",
        "стра́нный",
        "вызыва́ющий любопы́тство"
      ]
    },
    {
      "pos": "adj",
      "definition": "Clipping of bi-curious."
    },
    {
      "pos": "adj",
      "definition": "Interested in entering a romantic or sexual relationship with a specified group."
    },
    {
      "pos": "adj",
      "definition": "Careful, fastidious, particular; (specifically) demanding a high standard of excellence, difficult to satisfy."
    },
    {
      "pos": "adj",
      "definition": "Carefully or artfully constructed; made with great elegance or skill."
    },
    {
      "pos": "adj",
      "definition": "Containing or pertaining to trivalent curium."
    }
  ],
  "relations": {
    "synonyms": [
      "funny",
      "odd"
    ]
  }
}