{
  "word": "ever",
  "ipa": "/ɛvɝ/",
  "wiktionary_senses": [
    {
      "pos": "adv",
      "definition": "Always, frequently, forever.",
      "translations_ru": [
        "всегда́"
      ]
    },
    {
      "pos": "adv",
      "definition": "Continuously, constantly, all the time (for the complete duration)."
    },
    {
      "pos": "adv",
      "definition": "At any time.",
      "translations_ru": [
        "когда́-либо"
      ]
    },
    {
      "pos": "adv",
      "definition": "As intensifier following an interrogative word."
    },
    {
      "pos": "adv",
      "definition": "Indicates experiential aspect, once; has or have (done something) before."
    },
    {
      "pos": "adj",
      "definition": "Occurring at any time, occurring even but once during a timespan."
    },
    {
      "pos": "det",
      "definition": "Shortening of every"
    }
  ],
  "relations": {
    "antonyms": [
      "never"
    ]
  }
}