{
  "word": "fabric",
  "ipa": "/fæbɹɪk/",
  "wiktionary_senses": [
    {
      "pos": "noun",
      "definition": "An edifice or building.",
      "translations_ru": [
        "структу́ра",
        "зда́ние",
        "постро́йка"
      ]
    },
    {
      "pos": "noun",
      "definition": "The act of constructing, construction, fabrication.",
      "translations_ru": [
        "строи́тельство"
      ]
    },
    {
      "pos": "noun",
      "definition": "The structure of anything, the manner in which the parts of a thing are united; workmanship, texture, make."
    },
    {
      "pos": "noun",
      "definition": "The physical material of a building."
    },
    {
      "pos": "noun",
      "definition": "The framework underlying a structure.",
      "translations_ru": [
        "структу́ра"
      ]
    },
    {
      "pos": "noun",
      "definition": "A material made of fibers, a textile or cloth.",
      "translations_ru": [
        "ткань",
        "материа́л",
        "мате́рия"
      ]
    },
    {
      "pos": "noun",
      "definition": "The texture of a cloth.",
      "translations_ru": [
        "мате́рия"
      ]
    },
    {
      "pos": "noun",
      "definition": "The appearance of crystalline grains in a rock."
    },
    {
      "pos": "noun",
      "definition": "The fired clay material of pottery artifacts."
    },
    {
      "pos": "noun",
      "definition": "Interconnected nodes that look like a textile fabric when diagrammed."
    },
    {
      "pos": "verb",
      "definition": "To cover with fabric."
    }
  ],
  "relations": {
    "synonyms": [
      "material"
    ],
    "hypernyms": [
      "structure"
    ]
  }
}