{
  "word": "feed",
  "ipa": "/fid/",
  "wiktionary_senses": [
    {
      "pos": "verb",
      "definition": "To give (someone or something) food to eat.",
      "translations_ru": [
        "корми́ть"
      ]
    },
    {
      "pos": "verb",
      "definition": "To eat (usually of animals).",
      "translations_ru": [
        "есть",
        "ку́шать",
        "пита́ться"
      ]
    },
    {
      "pos": "verb",
      "definition": "To give (someone or something) to (someone or something else) as food."
    },
    {
      "pos": "verb",
      "definition": "To give to a machine to be processed.",
      "translations_ru": [
        "подава́ть",
        "пита́ть"
      ]
    },
    {
      "pos": "verb",
      "definition": "To supply (a machine) with something to be processed."
    },
    {
      "pos": "verb",
      "definition": "To satisfy, gratify, or minister to (a sense, taste, desire, etc.)."
    },
    {
      "pos": "verb",
      "definition": "To supply with something."
    },
    {
      "pos": "verb",
      "definition": "To graze; to cause to be cropped by feeding, as herbage by cattle."
    },
    {
      "pos": "verb",
      "definition": "To pass to."
    },
    {
      "pos": "verb",
      "definition": "To create the environment where another phonological rule can apply; to be applied before (another rule)."
    },
    {
      "pos": "verb",
      "definition": "To create the syntactic environment in which another syntactic rule is applied; to be applied before (another syntactic rule)."
    },
    {
      "pos": "noun",
      "definition": "Food given to (especially herbivorous) non-human animals.",
      "translations_ru": [
        "корм",
        "фура́ж",
        "пи́ща",
        "еда́",
        "пита́ние"
      ]
    },
    {
      "pos": "noun",
      "definition": "Something supplied continuously.",
      "translations_ru": [
        "пода́ча",
        "пита́ние"
      ]
    },
    {
      "pos": "noun",
      "definition": "The part of a machine that supplies the material to be operated upon."
    },
    {
      "pos": "noun",
      "definition": "The forward motion of the material fed into a machine."
    },
    {
      "pos": "noun",
      "definition": "A meal."
    },
    {
      "pos": "noun",
      "definition": "A gathering to eat, especially in large quantities.",
      "translations_ru": [
        "обжираловка",
        "пирушка"
      ]
    },
    {
      "pos": "noun",
      "definition": "online content presented sequentially:"
    },
    {
      "pos": "noun",
      "definition": "online content presented sequentially:"
    },
    {
      "pos": "noun",
      "definition": "A straight man who delivers lines to the comedian during a performance."
    },
    {
      "pos": "verb",
      "definition": "simple past and past participle of fee"
    }
  ],
  "relations": {
    "synonyms": [
      "give",
      "prey",
      "run"
    ],
    "antonyms": [
      "starve"
    ],
    "hypernyms": [
      "introduce",
      "offer",
      "provide",
      "supply",
      "advance",
      "promote",
      "treat",
      "food",
      "work",
      "consume",
      "take",
      "move"
    ]
  }
}