{
  "word": "fraud",
  "ipa": "/fɹɔd/",
  "wiktionary_senses": [
    {
      "pos": "noun",
      "definition": "The crime of stealing or otherwise illegally obtaining money by use of deception tactics."
    },
    {
      "pos": "noun",
      "definition": "Any act of deception carried out for the purpose of unfair, undeserved or unlawful gain.",
      "translations_ru": [
        "моше́нничество",
        "жу́льничество",
        "афе́ра",
        "шу́лерство"
      ]
    },
    {
      "pos": "noun",
      "definition": "The assumption of a false identity to such deceptive end."
    },
    {
      "pos": "noun",
      "definition": "A person who performs any such trick.",
      "translations_ru": [
        "моше́нник",
        "жу́лик",
        "афери́ст",
        "шу́лер"
      ]
    },
    {
      "pos": "noun",
      "definition": "A trap or snare."
    },
    {
      "pos": "verb",
      "definition": "To defraud."
    }
  ],
  "relations": {
    "hypernyms": [
      "cheat",
      "crime"
    ]
  }
}