{
  "word": "human",
  "ipa": "/hjumʌn/",
  "wiktionary_senses": [
    {
      "pos": "adj",
      "definition": "Of or belonging to the species Homo sapiens or its closest relatives.",
      "translations_ru": [
        "челове́ческий",
        "людско́й"
      ]
    },
    {
      "pos": "adj",
      "definition": "Having the nature or attributes of a human being.",
      "translations_ru": [
        "челове́ческий",
        "людско́й"
      ]
    },
    {
      "pos": "noun",
      "definition": "A highly intelligent ape with fine and short body hair; the most abundant species of primate, with members found on every continent (Homo sapiens)."
    },
    {
      "pos": "noun",
      "definition": "A highly intelligent ape with fine and short body hair; the most abundant species of primate, with members found on every continent (Homo sapiens)."
    },
    {
      "pos": "noun",
      "definition": "A highly intelligent ape with fine and short body hair; the most abundant species of primate, with members found on every continent (Homo sapiens)."
    },
    {
      "pos": "noun",
      "definition": "Any hominid of the genus Homo."
    },
    {
      "pos": "verb",
      "definition": "To behave as or become, or to cause to behave as or become, a human."
    },
    {
      "pos": "name",
      "definition": "A surname."
    },
    {
      "pos": "name",
      "definition": "The language supposedly spoken by humans"
    },
    {
      "pos": "name",
      "definition": "Alternative letter-case form of human used in works that capitalize the names of all sentient species"
    }
  ],
  "relations": {
    "synonyms": [
      "man"
    ]
  }
}