{
  "word": "impressive",
  "ipa": "/ɪmpɹɛsɪv/",
  "wiktionary_senses": [
    {
      "pos": "adj",
      "definition": "Making, or tending to make, a positive impression; having power to impress.",
      "translations_ru": [
        "впечатля́ющий",
        "внуши́тельный"
      ]
    },
    {
      "pos": "adj",
      "definition": "Capable of being impressed.",
      "translations_ru": [
        "впечатли́тельный"
      ]
    },
    {
      "pos": "adj",
      "definition": "Appealing."
    }
  ],
  "relations": {}
}