{
  "word": "issue",
  "ipa": "/ɪʃu/",
  "wiktionary_senses": [
    {
      "pos": "noun",
      "definition": "The action or an instance of flowing or coming out, an outflow"
    },
    {
      "pos": "noun",
      "definition": "The action or an instance of flowing or coming out, an outflow"
    },
    {
      "pos": "noun",
      "definition": "Someone or something that flows out or comes out"
    },
    {
      "pos": "noun",
      "definition": "Someone or something that flows out or comes out",
      "translations_ru": [
        "пото́мство",
        "пото́мок"
      ]
    },
    {
      "pos": "noun",
      "definition": "Someone or something that flows out or comes out"
    },
    {
      "pos": "noun",
      "definition": "Someone or something that flows out or comes out"
    },
    {
      "pos": "noun",
      "definition": "Someone or something that flows out or comes out",
      "translations_ru": [
        "урожа́й",
        "вы́работка"
      ]
    },
    {
      "pos": "noun",
      "definition": "Someone or something that flows out or comes out"
    },
    {
      "pos": "noun",
      "definition": "Someone or something that flows out or comes out"
    },
    {
      "pos": "noun",
      "definition": "Someone or something that flows out or comes out"
    },
    {
      "pos": "noun",
      "definition": "Someone or something that flows out or comes out"
    },
    {
      "pos": "noun",
      "definition": "Someone or something that flows out or comes out",
      "translations_ru": [
        "вы́пуск",
        "изда́ние"
      ]
    },
    {
      "pos": "noun",
      "definition": "Someone or something that flows out or comes out"
    },
    {
      "pos": "noun",
      "definition": "Someone or something that flows out or comes out"
    },
    {
      "pos": "noun",
      "definition": "Someone or something that flows out or comes out",
      "translations_ru": [
        "эми́ссия"
      ]
    },
    {
      "pos": "noun",
      "definition": "Someone or something that flows out or comes out"
    },
    {
      "pos": "noun",
      "definition": "The means or opportunity by which something flows or comes out, particularly"
    },
    {
      "pos": "noun",
      "definition": "The means or opportunity by which something flows or comes out"
    },
    {
      "pos": "noun",
      "definition": "The place where something flows or comes out, an outlet"
    },
    {
      "pos": "noun",
      "definition": "The place where something flows or comes out, an outlet"
    },
    {
      "pos": "noun",
      "definition": "The action or an instance of sending something out, particularly"
    },
    {
      "pos": "noun",
      "definition": "The action or an instance of sending something out"
    },
    {
      "pos": "noun",
      "definition": "The action or an instance of sending something out"
    },
    {
      "pos": "noun",
      "definition": "The action or an instance of sending something out"
    },
    {
      "pos": "noun",
      "definition": "The action or an instance of sending something out"
    },
    {
      "pos": "noun",
      "definition": "Any question or situation to be resolved, particularly"
    },
    {
      "pos": "noun",
      "definition": "Any question or situation to be resolved"
    },
    {
      "pos": "noun",
      "definition": "Any question or situation to be resolved"
    },
    {
      "pos": "noun",
      "definition": "Any question or situation to be resolved"
    },
    {
      "pos": "noun",
      "definition": "Any question or situation to be resolved",
      "translations_ru": [
        "пробле́ма",
        "вопро́с",
        "пункт",
        "те́ма"
      ]
    },
    {
      "pos": "noun",
      "definition": "The action or an instance of concluding something"
    },
    {
      "pos": "noun",
      "definition": "The action or an instance of concluding something",
      "translations_ru": [
        "отпра́вка",
        "отсы́лка"
      ]
    },
    {
      "pos": "noun",
      "definition": "The end result of an event or events, any result or outcome, particularly"
    },
    {
      "pos": "noun",
      "definition": "The end result of an event or events, any result or outcome"
    },
    {
      "pos": "noun",
      "definition": "The end result of an event or events, any result or outcome",
      "translations_ru": [
        "исхо́д",
        "результа́т"
      ]
    },
    {
      "pos": "noun",
      "definition": "The action or an instance of feeling some emotion."
    },
    {
      "pos": "noun",
      "definition": "The action or an instance of leaving any state or condition."
    },
    {
      "pos": "verb",
      "definition": "To flow out, to proceed from, to come out or from."
    },
    {
      "pos": "verb",
      "definition": "To rush out, to sally forth."
    },
    {
      "pos": "verb",
      "definition": "To extend into, to open onto."
    },
    {
      "pos": "verb",
      "definition": "To turn out in a certain way, to result in."
    },
    {
      "pos": "verb",
      "definition": "To end up as, to turn out being, to become as a result."
    },
    {
      "pos": "verb",
      "definition": "To come to a point in fact or law on which the parties join issue."
    },
    {
      "pos": "verb",
      "definition": "To send out; to put into circulation."
    },
    {
      "pos": "verb",
      "definition": "To deliver for use."
    },
    {
      "pos": "verb",
      "definition": "To deliver by authority."
    },
    {
      "pos": "noun",
      "definition": "A Monacan Indian; a member of a Mestee group originating in Amherst County, Virginia."
    }
  ],
  "relations": {
    "synonyms": [
      "supply",
      "number",
      "subject",
      "matter",
      "release",
      "return",
      "take",
      "result"
    ],
    "antonyms": [
      "recall"
    ],
    "hypernyms": [
      "fund",
      "store",
      "stock",
      "come",
      "supply",
      "content",
      "communicate",
      "relation",
      "air",
      "write",
      "escape",
      "beginning"
    ]
  }
}