{
  "word": "none",
  "ipa": "/nʌn/",
  "wiktionary_senses": [
    {
      "pos": "pron",
      "definition": "Not any of a given number or group."
    },
    {
      "pos": "pron",
      "definition": "Not any of a given number or group."
    },
    {
      "pos": "pron",
      "definition": "Not any of a given number or group.",
      "translations_ru": [
        "никто́"
      ]
    },
    {
      "pos": "det",
      "definition": "Not any; no (usually used only before a vowel or h)"
    },
    {
      "pos": "adv",
      "definition": "To no extent, in no way."
    },
    {
      "pos": "adv",
      "definition": "Not at all, not very."
    },
    {
      "pos": "adv",
      "definition": "No, not."
    },
    {
      "pos": "noun",
      "definition": "A person without religious affiliation."
    },
    {
      "pos": "noun",
      "definition": "Alternative form of nones: the ninth hour after dawn; (Christianity) the religious service appointed to this hour."
    },
    {
      "pos": "noun",
      "definition": "Synonym of midafternoon: the time around or following noon or nones."
    }
  ],
  "relations": {
    "hypernyms": [
      "hour",
      "service"
    ]
  }
}