{
  "word": "nursery",
  "ipa": "/nɝsɝi/",
  "wiktionary_senses": [
    {
      "pos": "noun",
      "definition": "A place where nursing (“breastfeeding”) or the raising of children is carried on.",
      "translations_ru": [
        "де́тская ко́мната",
        "де́тская"
      ]
    },
    {
      "pos": "noun",
      "definition": "A place where nursing (“breastfeeding”) or the raising of children is carried on.",
      "translations_ru": [
        "я́сли",
        "де́тский сад",
        "де́тская ко́мната",
        "де́тская"
      ]
    },
    {
      "pos": "noun",
      "definition": "A place where nursing (“breastfeeding”) or the raising of children is carried on."
    },
    {
      "pos": "noun",
      "definition": "A place where anything is fostered and growth promoted."
    },
    {
      "pos": "noun",
      "definition": "A place where anything is fostered and growth promoted.",
      "translations_ru": [
        "пито́мник"
      ]
    },
    {
      "pos": "noun",
      "definition": "A place where anything is fostered and growth promoted.",
      "translations_ru": [
        "расса́дник",
        "пито́мник"
      ]
    },
    {
      "pos": "noun",
      "definition": "A place where anything is fostered and growth promoted."
    },
    {
      "pos": "noun",
      "definition": "Something which educates and nurtures."
    },
    {
      "pos": "noun",
      "definition": "Ellipsis of nursery cannon (“a carom shot involving balls that are very close together”)."
    },
    {
      "pos": "noun",
      "definition": "Someone or something that is nursed; a nursling."
    },
    {
      "pos": "noun",
      "definition": "The act of nursing or rearing."
    }
  ],
  "relations": {}
}