{
  "word": "rent",
  "ipa": "/ɹɛnt/",
  "wiktionary_senses": [
    {
      "pos": "noun",
      "definition": "A payment made by a tenant at intervals in order to lease a property.",
      "translations_ru": [
        "кварти́рная пла́та",
        "квартпла́та",
        "аре́ндная пла́та",
        "аре́нда",
        "ре́нта"
      ]
    },
    {
      "pos": "noun",
      "definition": "A similar payment for the use of a product, equipment or a service."
    },
    {
      "pos": "noun",
      "definition": "A profit from possession of a valuable right, as a restricted license to engage in a trade or business."
    },
    {
      "pos": "noun",
      "definition": "An object for which rent is charged or paid."
    },
    {
      "pos": "noun",
      "definition": "Income; revenue."
    },
    {
      "pos": "noun",
      "definition": "An amount of virtual currency paid by a player to preserve their character, inventory, etc. between gameplay sessions in a multi-user dungeon."
    },
    {
      "pos": "verb",
      "definition": "To take a lease of premises in exchange for rent.",
      "translations_ru": [
        "снима́ть",
        "снять"
      ]
    },
    {
      "pos": "verb",
      "definition": "To grant a lease in return for rent.",
      "translations_ru": [
        "сдава́ть в аре́нду",
        "сдать в аре́нду",
        "сдава́ть внаём",
        "сдать внаём",
        "сдава́ть",
        "сдать"
      ]
    },
    {
      "pos": "verb",
      "definition": "To obtain or have temporary possession of an object (e.g. a movie) in exchange for money.",
      "translations_ru": [
        "брать напрока́т",
        "взять напрока́т",
        "нанима́ть",
        "наня́ть"
      ]
    },
    {
      "pos": "verb",
      "definition": "To be leased or let for rent."
    },
    {
      "pos": "noun",
      "definition": "A tear or rip in some surface.",
      "translations_ru": [
        "проре́ха"
      ]
    },
    {
      "pos": "noun",
      "definition": "A division or schism."
    },
    {
      "pos": "verb",
      "definition": "simple past and past participle of rend"
    },
    {
      "pos": "adj",
      "definition": "That has been torn or rent; ripped; torn."
    },
    {
      "pos": "name",
      "definition": "A surname."
    }
  ],
  "relations": {
    "synonyms": [
      "rip",
      "split",
      "tear",
      "take"
    ],
    "hypernyms": [
      "get",
      "tear",
      "issue",
      "return",
      "take",
      "give",
      "contract"
    ]
  }
}