{
  "word": "result",
  "ipa": "/ɹɪzʌlt/",
  "wiktionary_senses": [
    {
      "pos": "verb",
      "definition": "To proceed, spring up or rise, as a consequence, from facts, arguments, premises, combination of circumstances, consultation, thought or endeavor.",
      "translations_ru": [
        "проистека́ть",
        "происте́чь"
      ]
    },
    {
      "pos": "verb",
      "definition": "To have as a consequence; to lead to; to bring about",
      "translations_ru": [
        "приводи́ть"
      ]
    },
    {
      "pos": "verb",
      "definition": "To return to the proprietor (or heirs) after a reversion."
    },
    {
      "pos": "verb",
      "definition": "To leap back; to rebound."
    },
    {
      "pos": "noun",
      "definition": "That which results; the conclusion or end to which any course or condition of things leads, or which is obtained by any process or operation; consequence or effect.",
      "translations_ru": [
        "результа́т",
        "ито́г",
        "исхо́д"
      ]
    },
    {
      "pos": "noun",
      "definition": "The final product, beneficial or tangible effect(s) achieved by effort.",
      "translations_ru": [
        "результа́т",
        "плод",
        "проду́кт"
      ]
    },
    {
      "pos": "noun",
      "definition": "The decision or determination of a council or deliberative assembly; a resolve; a decree."
    },
    {
      "pos": "noun",
      "definition": "A flying back; resilience."
    },
    {
      "pos": "noun",
      "definition": "The final score in a game.",
      "translations_ru": [
        "результа́т",
        "счёт"
      ]
    },
    {
      "pos": "noun",
      "definition": "A positive or favourable outcome for someone."
    },
    {
      "pos": "intj",
      "definition": "An exclamation of joy following a favorable outcome."
    }
  ],
  "relations": {
    "synonyms": [
      "solution"
    ],
    "hypernyms": [
      "happen",
      "occur",
      "pass",
      "prove",
      "conclusion",
      "finish",
      "statement",
      "produce"
    ]
  }
}