{
  "word": "sale",
  "ipa": "/seɪl/",
  "wiktionary_senses": [
    {
      "pos": "noun",
      "definition": "An exchange of goods or services for currency or credit.",
      "translations_ru": [
        "прода́жа"
      ]
    },
    {
      "pos": "noun",
      "definition": "Ellipsis of discount sale (“the sale of goods at reduced prices”).",
      "translations_ru": [
        "распрода́жа",
        "сейл",
        "сэйл"
      ]
    },
    {
      "pos": "noun",
      "definition": "The act of putting up for auction to the highest bidder.",
      "translations_ru": [
        "аукцио́н",
        "торги́"
      ]
    },
    {
      "pos": "noun",
      "definition": "A hall."
    },
    {
      "pos": "name",
      "definition": "A town in the Metropolitan Borough of Trafford, Greater Manchester, England, historically in Cheshire (OS grid ref SJ9892)."
    },
    {
      "pos": "name",
      "definition": "A town in the Shire of Wellington, Gippsland, Victoria, Australia, named after Robert Sale."
    },
    {
      "pos": "name",
      "definition": "A surname."
    }
  ],
  "relations": {
    "hypernyms": [
      "occasion",
      "agreement",
      "understanding"
    ]
  }
}