{
  "word": "satisfy",
  "ipa": "/sætʌsfaɪ/",
  "wiktionary_senses": [
    {
      "pos": "verb",
      "definition": "To be enough (for)"
    },
    {
      "pos": "verb",
      "definition": "To be enough (for)"
    },
    {
      "pos": "verb",
      "definition": "To be enough (for)"
    },
    {
      "pos": "verb",
      "definition": "To pay to the extent of what is claimed or due."
    },
    {
      "pos": "verb",
      "definition": "To answer or discharge (a claim, debt, legal demand, etc.); to give compensation for."
    },
    {
      "pos": "verb",
      "definition": "To cause (a sentence) to be true when the sentence is interpreted in one's universe."
    },
    {
      "pos": "verb",
      "definition": "To convince by ascertaining; to free from doubt."
    }
  ],
  "relations": {
    "hypernyms": [
      "provide",
      "supply",
      "fill",
      "fit",
      "meet",
      "change"
    ]
  }
}