{
  "word": "seal",
  "ipa": "/sil/",
  "wiktionary_senses": [
    {
      "pos": "noun",
      "definition": "A pinniped (Pinnipedia), particularly an earless seal (true seal) or eared seal.",
      "translations_ru": [
        "тюле́нь"
      ]
    },
    {
      "pos": "verb",
      "definition": "To hunt seals."
    },
    {
      "pos": "noun",
      "definition": "A stamp used to impress a design on a soft substance such as wax.",
      "translations_ru": [
        "печа́ть"
      ]
    },
    {
      "pos": "noun",
      "definition": "An impression of such stamp on wax, paper or other material used for sealing."
    },
    {
      "pos": "noun",
      "definition": "A facsimile of an impression of such stamp that is a mark or symbol of an office or organisation.",
      "translations_ru": [
        "печа́ть"
      ]
    },
    {
      "pos": "noun",
      "definition": "Anything that secures or authenticates."
    },
    {
      "pos": "noun",
      "definition": "Something which will be visibly damaged if a covering or container is opened, and which may or may not bear an official design.",
      "translations_ru": [
        "печа́ть",
        "пло́мба"
      ]
    },
    {
      "pos": "noun",
      "definition": "Confirmation or approval, or an indication of this."
    },
    {
      "pos": "noun",
      "definition": "Something designed to prevent liquids or gases from leaking through a joint.",
      "translations_ru": [
        "уплотни́тель",
        "са́льник",
        "прокла́дка"
      ]
    },
    {
      "pos": "noun",
      "definition": "A tight closure, secure against leakage.",
      "translations_ru": [
        "уплотне́ние",
        "герметиза́ция"
      ]
    },
    {
      "pos": "noun",
      "definition": "A chakra."
    },
    {
      "pos": "verb",
      "definition": "To place a seal on (a document).",
      "translations_ru": [
        "запеча́тывать"
      ]
    },
    {
      "pos": "verb",
      "definition": "To mark with a stamp, as an evidence of standard exactness, legal size, or merchantable quality."
    },
    {
      "pos": "verb",
      "definition": "To fasten (something) so that it cannot be opened without visible damage.",
      "translations_ru": [
        "запеча́тывать"
      ]
    },
    {
      "pos": "verb",
      "definition": "To prevent people or vehicles from crossing (something).",
      "translations_ru": [
        "закрыва́ть"
      ]
    },
    {
      "pos": "verb",
      "definition": "To close securely to prevent leakage.",
      "translations_ru": [
        "запеча́тывать"
      ]
    },
    {
      "pos": "verb",
      "definition": "To place in a sealed container.",
      "translations_ru": [
        "запеча́тывать"
      ]
    },
    {
      "pos": "verb",
      "definition": "To place a notation of one's next move in a sealed envelope to be opened after an adjournment."
    },
    {
      "pos": "verb",
      "definition": "To guarantee."
    },
    {
      "pos": "verb",
      "definition": "To fix, as a piece of iron in a wall, with cement or plaster, etc."
    },
    {
      "pos": "verb",
      "definition": "To close by means of a seal."
    },
    {
      "pos": "verb",
      "definition": "To bind eternally as family members."
    },
    {
      "pos": "verb",
      "definition": "To form a sacred commitment."
    },
    {
      "pos": "verb",
      "definition": "To fry (meat) at a high temperature to retain the juices."
    },
    {
      "pos": "verb",
      "definition": "To tie up animals (especially cattle) in their stalls."
    },
    {
      "pos": "noun",
      "definition": "Ellipsis of Navy SEAL (“member of the Sea, Air, Land unit”)."
    },
    {
      "pos": "name",
      "definition": "A surname."
    },
    {
      "pos": "name",
      "definition": "A village in Sevenoaks district, Kent, England."
    }
  ],
  "relations": {
    "synonyms": [
      "stamp"
    ],
    "hypernyms": [
      "stamp",
      "close",
      "shut",
      "honor",
      "hunt",
      "run",
      "coat",
      "decide",
      "determine"
    ]
  }
}