{
  "word": "seed",
  "ipa": "/sid/",
  "wiktionary_senses": [
    {
      "pos": "noun",
      "definition": "Any propagative portion of a plant which may be sown, such as true seeds, seed-like fruits, tubers, or bulbs."
    },
    {
      "pos": "noun",
      "definition": "Any propagative portion of a plant which may be sown, such as true seeds, seed-like fruits, tubers, or bulbs."
    },
    {
      "pos": "noun",
      "definition": "Any propagative portion of a plant which may be sown, such as true seeds, seed-like fruits, tubers, or bulbs.",
      "translations_ru": [
        "се́мя",
        "семена́"
      ]
    },
    {
      "pos": "noun",
      "definition": "An amount of seeds that cannot be readily counted."
    },
    {
      "pos": "noun",
      "definition": "A fragment of coral."
    },
    {
      "pos": "noun",
      "definition": "Semen.",
      "translations_ru": [
        "се́мя"
      ]
    },
    {
      "pos": "noun",
      "definition": "A precursor."
    },
    {
      "pos": "noun",
      "definition": "The initial state, condition or position of a changing, growing or developing process; the ultimate precursor in a defined chain of precursors."
    },
    {
      "pos": "noun",
      "definition": "The initial state, condition or position of a changing, growing or developing process; the ultimate precursor in a defined chain of precursors."
    },
    {
      "pos": "noun",
      "definition": "The initial state, condition or position of a changing, growing or developing process; the ultimate precursor in a defined chain of precursors."
    },
    {
      "pos": "noun",
      "definition": "The initial state, condition or position of a changing, growing or developing process; the ultimate precursor in a defined chain of precursors."
    },
    {
      "pos": "noun",
      "definition": "The initial state, condition or position of a changing, growing or developing process; the ultimate precursor in a defined chain of precursors."
    },
    {
      "pos": "noun",
      "definition": "Offspring, descendants, progeny."
    },
    {
      "pos": "noun",
      "definition": "Race; generation; birth."
    },
    {
      "pos": "noun",
      "definition": "A small particle, bubble, or imperfection that serves as a nucleation point for some process."
    },
    {
      "pos": "noun",
      "definition": "A small bubble formed in imperfectly fused glass."
    },
    {
      "pos": "noun",
      "definition": "A child."
    },
    {
      "pos": "verb",
      "definition": "To plant or sow an area with seeds.",
      "translations_ru": [
        "засевать",
        "высевать",
        "засеивать",
        "высеивать",
        "засеять",
        "посеять"
      ]
    },
    {
      "pos": "verb",
      "definition": "To shed seeds (refers to plants)"
    },
    {
      "pos": "verb",
      "definition": "To cover thinly with something scattered; to ornament with seedlike decorations."
    },
    {
      "pos": "verb",
      "definition": "To start; to provide, assign or determine the initial resources for, position of, state of."
    },
    {
      "pos": "verb",
      "definition": "To allocate a seeding to a competitor."
    },
    {
      "pos": "verb",
      "definition": "To leave (files) available for others to download through peer-to-peer file sharing protocols (e.g. BitTorrent)."
    },
    {
      "pos": "verb",
      "definition": "To be qualified to compete, especially in a quarter-final, semi-final, or final."
    },
    {
      "pos": "verb",
      "definition": "To scatter small particles within (a cloud or airmass) in order to trigger the formation of rain."
    },
    {
      "pos": "verb",
      "definition": "To produce seed."
    },
    {
      "pos": "verb",
      "definition": "To grow to maturity."
    },
    {
      "pos": "verb",
      "definition": "To ejaculate inside the penetratee during intercourse, especially in the rectum."
    },
    {
      "pos": "verb",
      "definition": "simple past and past participle of see"
    },
    {
      "pos": "name",
      "definition": "A surname."
    }
  ],
  "relations": {
    "synonyms": [
      "source"
    ],
    "hypernyms": [
      "order",
      "place",
      "rate",
      "rank",
      "range",
      "finance",
      "player",
      "spill",
      "shed",
      "fruit",
      "pull",
      "remove",
      "take",
      "inspiration",
      "lay",
      "put",
      "position",
      "set",
      "process",
      "treat",
      "bear"
    ]
  }
}