{
  "word": "something",
  "ipa": "/sʌmθɪŋ/",
  "wiktionary_senses": [
    {
      "pos": "pron",
      "definition": "An uncertain or unspecified thing; one thing.",
      "translations_ru": [
        "что́-то",
        "не́что",
        "кое-что́"
      ]
    },
    {
      "pos": "pron",
      "definition": "A quality to a moderate degree."
    },
    {
      "pos": "pron",
      "definition": "A talent or quality that is difficult to specify."
    },
    {
      "pos": "pron",
      "definition": "Somebody who or something that is superlative or notable in some way."
    },
    {
      "pos": "adj",
      "definition": "Having a characteristic that the speaker cannot specify."
    },
    {
      "pos": "adv",
      "definition": "Somewhat; to a degree."
    },
    {
      "pos": "adv",
      "definition": "Used to adverbialise a following adjective"
    },
    {
      "pos": "verb",
      "definition": "Designates an action whose name is forgotten by, unknown or unimportant to the user, e.g. from words of a song."
    },
    {
      "pos": "noun",
      "definition": "An object whose nature is yet to be defined."
    },
    {
      "pos": "noun",
      "definition": "An object whose name is forgotten by, unknown or unimportant to the user, e.g., from words of a song. Also used to refer to an object earlier indefinitely referred to as 'something' (pronoun sense)."
    }
  ],
  "relations": {}
}