{
  "word": "supply",
  "ipa": "/sʌplaɪ/",
  "wiktionary_senses": [
    {
      "pos": "verb",
      "definition": "To provide (something), to make (something) available for use.",
      "translations_ru": [
        "снабжа́ть",
        "снабди́ть",
        "поставля́ть",
        "поста́вить"
      ]
    },
    {
      "pos": "verb",
      "definition": "To furnish or equip with.",
      "translations_ru": [
        "снабжа́ть",
        "снабди́ть",
        "снаряжа́ть",
        "снаряди́ть"
      ]
    },
    {
      "pos": "verb",
      "definition": "To fill up, or keep full."
    },
    {
      "pos": "verb",
      "definition": "To compensate for, or make up a deficiency of.",
      "translations_ru": [
        "пополня́ть",
        "попо́лнить"
      ]
    },
    {
      "pos": "verb",
      "definition": "To serve instead of; to take the place of."
    },
    {
      "pos": "verb",
      "definition": "To act as a substitute."
    },
    {
      "pos": "verb",
      "definition": "To fill temporarily; to serve as substitute for another in, as a vacant place or office; to occupy; to have possession of."
    },
    {
      "pos": "noun",
      "definition": "The act of supplying.",
      "translations_ru": [
        "снабже́ние",
        "поста́вка",
        "предложе́ние"
      ]
    },
    {
      "pos": "noun",
      "definition": "An amount of something supplied.",
      "translations_ru": [
        "запа́с"
      ]
    },
    {
      "pos": "noun",
      "definition": "The market force that causes sellers to be both willing and able to sell a good or service, as measured by the amount of that good or service that is currently available to be bought at any given price point; the amount itself."
    },
    {
      "pos": "noun",
      "definition": "Provisions.",
      "translations_ru": [
        "припа́сы"
      ]
    },
    {
      "pos": "noun",
      "definition": "An amount of money provided, as by Parliament or Congress, to meet the annual national expenditures."
    },
    {
      "pos": "noun",
      "definition": "Somebody, such as a teacher or clergyman, who temporarily fills the place of another; a substitute."
    },
    {
      "pos": "adv",
      "definition": "Supplely: in a supple manner, with suppleness."
    }
  ],
  "relations": {
    "hypernyms": [
      "give",
      "activity",
      "state",
      "say",
      "tell"
    ]
  }
}