{
  "word": "take",
  "ipa": "/teɪk/",
  "wiktionary_senses": [
    {
      "pos": "verb",
      "definition": "To get into one's hands, possession, or control, with or without force."
    },
    {
      "pos": "verb",
      "definition": "To get into one's hands, possession, or control, with or without force."
    },
    {
      "pos": "verb",
      "definition": "To get into one's hands, possession, or control, with or without force."
    },
    {
      "pos": "verb",
      "definition": "To get into one's hands, possession, or control, with or without force."
    },
    {
      "pos": "verb",
      "definition": "To get into one's hands, possession, or control, with or without force."
    },
    {
      "pos": "verb",
      "definition": "To get into one's hands, possession, or control, with or without force."
    },
    {
      "pos": "verb",
      "definition": "To get into one's hands, possession, or control, with or without force."
    },
    {
      "pos": "verb",
      "definition": "To receive or accept (something, especially something which was given)."
    },
    {
      "pos": "verb",
      "definition": "To receive or accept (something, especially something which was given)."
    },
    {
      "pos": "verb",
      "definition": "To receive or accept (something, especially something which was given)."
    },
    {
      "pos": "verb",
      "definition": "To receive or accept (something, especially something which was given)."
    },
    {
      "pos": "verb",
      "definition": "To receive or accept (something, especially something which was given)."
    },
    {
      "pos": "verb",
      "definition": "To receive or accept (something, especially something which was given).",
      "translations_ru": [
        "брать",
        "взять",
        "захва́тывать",
        "захвати́ть",
        "занима́ть",
        "заня́ть"
      ]
    },
    {
      "pos": "verb",
      "definition": "To remove."
    },
    {
      "pos": "verb",
      "definition": "To remove."
    },
    {
      "pos": "verb",
      "definition": "To remove."
    },
    {
      "pos": "verb",
      "definition": "To have sex with.",
      "translations_ru": [
        "брать",
        "взять"
      ]
    },
    {
      "pos": "verb",
      "definition": "To defeat (someone or something) in a fight."
    },
    {
      "pos": "verb",
      "definition": "To grasp or grip.",
      "translations_ru": [
        "брать",
        "взять"
      ]
    },
    {
      "pos": "verb",
      "definition": "To select or choose; to pick."
    },
    {
      "pos": "verb",
      "definition": "To select or choose; to pick."
    },
    {
      "pos": "verb",
      "definition": "To carry or lead (something or someone)."
    },
    {
      "pos": "verb",
      "definition": "To carry or lead (something or someone)."
    },
    {
      "pos": "verb",
      "definition": "To carry or lead (something or someone)."
    },
    {
      "pos": "verb",
      "definition": "To carry or lead (something or someone)."
    },
    {
      "pos": "verb",
      "definition": "To carry or lead (something or someone)."
    },
    {
      "pos": "verb",
      "definition": "To carry or lead (something or someone)."
    },
    {
      "pos": "verb",
      "definition": "To use as a means of transportation."
    },
    {
      "pos": "verb",
      "definition": "To obtain for use by payment or lease."
    },
    {
      "pos": "verb",
      "definition": "To obtain for use by payment or lease."
    },
    {
      "pos": "verb",
      "definition": "To receive (medicine or drugs) into one's body, e.g. by inhalation or swallowing; to ingest.",
      "translations_ru": [
        "принима́ть",
        "приня́ть"
      ]
    },
    {
      "pos": "verb",
      "definition": "To consume (food or drink)."
    },
    {
      "pos": "verb",
      "definition": "To undergo; to put oneself into, to be subjected to."
    },
    {
      "pos": "verb",
      "definition": "To experience or feel."
    },
    {
      "pos": "verb",
      "definition": "To submit to; to endure (without ill humor, resentment, or physical failure)."
    },
    {
      "pos": "verb",
      "definition": "To suffer; to endure (a hardship or damage)."
    },
    {
      "pos": "verb",
      "definition": "To participate in."
    },
    {
      "pos": "verb",
      "definition": "To cause to change to a specified state or condition."
    },
    {
      "pos": "verb",
      "definition": "To regard in a specified way."
    },
    {
      "pos": "verb",
      "definition": "To conclude or form (a decision or an opinion) in the mind."
    },
    {
      "pos": "verb",
      "definition": "To understand (especially in a specified way)."
    },
    {
      "pos": "verb",
      "definition": "To believe, to accept the statements of."
    },
    {
      "pos": "verb",
      "definition": "To assume or suppose; to reckon; to regard or consider."
    },
    {
      "pos": "verb",
      "definition": "To draw, derive, or deduce (a meaning from something)."
    },
    {
      "pos": "verb",
      "definition": "To derive (as a title); to obtain from a source."
    },
    {
      "pos": "verb",
      "definition": "To catch or contract (an illness, etc.)."
    },
    {
      "pos": "verb",
      "definition": "To come upon or catch (in a particular state or situation)."
    },
    {
      "pos": "verb",
      "definition": "To captivate or charm; to gain or secure the interest or affection of."
    },
    {
      "pos": "verb",
      "definition": "To absorb or be impregnated by (dye, ink, etc.); to be susceptible to being treated by (polish, etc.)."
    },
    {
      "pos": "verb",
      "definition": "To let in (water)."
    },
    {
      "pos": "verb",
      "definition": "To require (a person, resource or thing in order to achieve an outcome)."
    },
    {
      "pos": "verb",
      "definition": "To proceed to fill."
    },
    {
      "pos": "verb",
      "definition": "To fill, occupy, require, or use up (space)."
    },
    {
      "pos": "verb",
      "definition": "To fill or require: to last or expend (an amount of time).",
      "translations_ru": [
        "занима́ть",
        "заня́ть"
      ]
    },
    {
      "pos": "verb",
      "definition": "To avail oneself of; to exploit."
    },
    {
      "pos": "verb",
      "definition": "To practice; perform; execute; carry out; do."
    },
    {
      "pos": "verb",
      "definition": "To assume or perform (a form or role)."
    },
    {
      "pos": "verb",
      "definition": "To assume or perform (a form or role)."
    },
    {
      "pos": "verb",
      "definition": "To assume or perform (a form or role)."
    },
    {
      "pos": "verb",
      "definition": "To bind oneself by."
    },
    {
      "pos": "verb",
      "definition": "To go into, through, or along."
    },
    {
      "pos": "verb",
      "definition": "To go into, through, or along."
    },
    {
      "pos": "verb",
      "definition": "To have and use one's recourse to."
    },
    {
      "pos": "verb",
      "definition": "To ascertain or determine by measurement, examination or inquiry."
    },
    {
      "pos": "verb",
      "definition": "To write down; to get in, or as if in, writing."
    },
    {
      "pos": "verb",
      "definition": "To make (a photograph, film, or other reproduction of something).",
      "translations_ru": [
        "фотографи́ровать",
        "сфотографи́ровать",
        "снима́ть",
        "снять"
      ]
    },
    {
      "pos": "verb",
      "definition": "To make a picture, photograph, etc. of (a person, scene, etc.)."
    },
    {
      "pos": "verb",
      "definition": "To obtain money from, especially by swindling."
    },
    {
      "pos": "verb",
      "definition": "To apply oneself to the study of."
    },
    {
      "pos": "verb",
      "definition": "To deal with."
    },
    {
      "pos": "verb",
      "definition": "To consider in a particular way, or to consider as an example."
    },
    {
      "pos": "verb",
      "definition": "To decline to swing at (a pitched ball); to refrain from hitting at, and allow to pass."
    },
    {
      "pos": "verb",
      "definition": "To accept as an input to a relation."
    },
    {
      "pos": "verb",
      "definition": "To accept as an input to a relation."
    },
    {
      "pos": "verb",
      "definition": "To buy."
    },
    {
      "pos": "verb",
      "definition": "To get or accept (something) into one's possession."
    },
    {
      "pos": "verb",
      "definition": "To engage, take hold or have effect."
    },
    {
      "pos": "verb",
      "definition": "To engage, take hold or have effect."
    },
    {
      "pos": "verb",
      "definition": "To engage, take hold or have effect."
    },
    {
      "pos": "verb",
      "definition": "To engage, take hold or have effect."
    },
    {
      "pos": "verb",
      "definition": "To engage, take hold or have effect."
    },
    {
      "pos": "verb",
      "definition": "To become; to be affected in a specified way."
    },
    {
      "pos": "verb",
      "definition": "To be able to be accurately or beautifully photographed."
    },
    {
      "pos": "verb",
      "definition": "An intensifier."
    },
    {
      "pos": "verb",
      "definition": "To deliver, bring, give (something) to (someone)."
    },
    {
      "pos": "verb",
      "definition": "To give or deliver (a blow, to someone); to strike or hit."
    },
    {
      "pos": "verb",
      "definition": "To visit; to include in a course of travel."
    },
    {
      "pos": "verb",
      "definition": "To portray in a painting."
    },
    {
      "pos": "verb",
      "definition": "Used in phrasal verbs: take in, take off, take on, take out, take to, take something to, take up."
    },
    {
      "pos": "noun",
      "definition": "The or an act of taking.",
      "translations_ru": [
        "взятие"
      ]
    },
    {
      "pos": "noun",
      "definition": "Something that is taken; a haul."
    },
    {
      "pos": "noun",
      "definition": "Something that is taken; a haul."
    },
    {
      "pos": "noun",
      "definition": "An interpretation or view, opinion or assessment; perspective; a statement expressing such a position."
    },
    {
      "pos": "noun",
      "definition": "An approach, a (distinct) treatment."
    },
    {
      "pos": "noun",
      "definition": "A scene recorded (filmed) at one time, without an interruption or break; a recording of such a scene.",
      "translations_ru": [
        "дубль"
      ]
    },
    {
      "pos": "noun",
      "definition": "A recording of a musical performance made during an uninterrupted single recording period."
    },
    {
      "pos": "noun",
      "definition": "A visible (facial) response to something, especially something unexpected; a facial gesture in response to an event."
    },
    {
      "pos": "noun",
      "definition": "An instance of successful inoculation/vaccination."
    },
    {
      "pos": "noun",
      "definition": "A catch of the ball (in cricket, especially one by the wicket-keeper)."
    },
    {
      "pos": "noun",
      "definition": "The quantity of copy given to a compositor at one time."
    }
  ],
  "relations": {
    "synonyms": [
      "train"
    ],
    "hypernyms": [
      "experience",
      "get",
      "receive",
      "act",
      "move",
      "position",
      "ask",
      "demand",
      "involve",
      "need",
      "require",
      "see",
      "work",
      "find",
      "apply",
      "use",
      "decide",
      "determine",
      "buy",
      "swear",
      "change",
      "head",
      "enter",
      "record",
      "bang",
      "bed",
      "know",
      "love",
      "screw",
      "carry",
      "transport",
      "become",
      "go",
      "concern",
      "refer",
      "touch",
      "accept",
      "feature",
      "hold",
      "cross",
      "cover",
      "track",
      "fit",
      "suit",
      "win"
    ]
  }
}